{
  "annotations": [
    {
      "id": "3/26/2026, 3:11:10 PM",
      "taskId": "69c4f7cad7b7afd6a25f5338",
      "page": "3",
      "answerPdfImageId": null,
      "answerPdfId": "69c4f6b5d7b7afd6a25f5012",
      "userId": "69c3b24d13f7f5a8f834f174",
      "questionDefinitionId": "69c4d988d70ea90845a4377b",
      "iconUrl": "/check.png",
      "question": 1,
      "timeStamps": "3/26/2026, 3:11:10 PM",
      "x": 781.625,
      "y": 384.421875,
      "width": 150,
      "height": 80,
      "synced": false,
      "mark": 2,
      "parentQuestionId": null
    }
  ],
  "comments": []
}